py_nillion_client-0.5.0.dist-info/METADATA
py_nillion_client-0.5.0.dist-info/WHEEL
py_nillion_client-0.5.0.dist-info/license_files/LICENSE
py_nillion_client/py_nillion_client.pyi
py_nillion_client/py.typed
py_nillion_client/nillion/meta/v1/tx_pb2.py
py_nillion_client/nillion/meta/v1/__init__.py
py_nillion_client/nillion/meta/__init__.py
py_nillion_client/nillion/__init__.py
py_nillion_client/__init__.py
py_nillion_client/py_nillion_client.abi3.so
py_nillion_client-0.5.0.dist-info/RECORD
