Metadata-Version: 2.3
Name: py-nillion-client
Version: 0.5.0
Classifier: Programming Language :: Rust
Classifier: Programming Language :: Python :: Implementation :: CPython
Classifier: Programming Language :: Python :: Implementation :: PyPy
Classifier: License :: OSI Approved :: Apache Software License
Requires-Dist: protobuf >=4.21.6, <5.0.dev0
Requires-Dist: maturin ==1.6.0 ; extra == 'dev'
Requires-Dist: maturin[zig] ==1.6.0 ; extra == 'dev'
Requires-Dist: pytest ==8.0.0 ; extra == 'dev'
Requires-Dist: cosmpy ==0.9.2 ; extra == 'dev'
Requires-Dist: pyyaml ==6.0.1 ; extra == 'dev'
Provides-Extra: dev
License-File: LICENSE
Summary: Python client for Nillion network and utilities.
License: Apache-2.0
Requires-Python: >=3.10
